{
  "_format": "hh-sol-cache-2",
  "files": {
    "/home/ubuntu1/web3go/mintynew/contracts/STARNFT7.sol": {
      "lastModificationDate": 1628667868167,
      "contentHash": "716df85c095b1b8a33c897e64e76492e",
      "sourceName": "contracts/STARNFT7.sol",
      "solcConfig": {
        "version": "0.8.4",
        "settings": {
          "optimizer": {
            "enabled": false,
            "runs": 200
          },
          "outputSelection": {
            "*": {
              "*": [
                "abi",
                "evm.bytecode",
                "evm.deployedBytecode",
                "evm.methodIdentifiers"
              ],
              "": [
                "ast"
              ]
            }
          }
        }
      },
      "imports": [
        "@openzeppelin/contracts/token/ERC721/ERC721.sol",
        "@openzeppelin/contracts/utils/Counters.sol",
        "@openzeppelin/contracts/access/Ownable.sol"
      ],
      "versionPragmas": [
        "^0.8.0"
      ],
      "artifacts": [
        "STARNFT7"
      ]
    },
    "/home/ubuntu1/web3go/mintynew/node_modules/@openzeppelin/contracts/token/ERC721/ERC721.sol": {
      "lastModificationDate": 1628667868399,
      "contentHash": "8fc7506d6ee32c5fbc527b0c42f0e615",
      "sourceName": "@openzeppelin/contracts/token/ERC721/ERC721.sol",
      "solcConfig": {
        "version": "0.8.4",
        "settings": {
          "optimizer": {
            "enabled": false,
            "runs": 200
          },
          "outputSelection": {
            "*": {
              "*": [
                "abi",
                "evm.bytecode",
                "evm.deployedBytecode",
                "evm.methodIdentifiers"
              ],
              "": [
                "ast"
              ]
            }
          }
        }
      },
      "imports": [
        "./IERC721.sol",
        "./IERC721Receiver.sol",
        "./extensions/IERC721Metadata.sol",
        "../../utils/Address.sol",
        "../../utils/Context.sol",
        "../../utils/Strings.sol",
        "../../utils/introspection/ERC165.sol"
      ],
      "versionPragmas": [
        "^0.8.0"
      ],
      "artifacts": [
        "ERC721"
      ]
    },
    "/home/ubuntu1/web3go/mintynew/node_modules/@openzeppelin/contracts/utils/Counters.sol": {
      "lastModificationDate": 1628667868399,
      "contentHash": "86ddbfba30a7d811a86f54416c364be3",
      "sourceName": "@openzeppelin/contracts/utils/Counters.sol",
      "solcConfig": {
        "version": "0.8.4",
        "settings": {
          "optimizer": {
            "enabled": false,
            "runs": 200
          },
          "outputSelection": {
            "*": {
              "*": [
                "abi",
                "evm.bytecode",
                "evm.deployedBytecode",
                "evm.methodIdentifiers"
              ],
              "": [
                "ast"
              ]
            }
          }
        }
      },
      "imports": [],
      "versionPragmas": [
        "^0.8.0"
      ],
      "artifacts": [
        "Counters"
      ]
    },
    "/home/ubuntu1/web3go/mintynew/node_modules/@openzeppelin/contracts/access/Ownable.sol": {
      "lastModificationDate": 1628667868395,
      "contentHash": "17d9f40220b0ab370db2c77e7c92c4ef",
      "sourceName": "@openzeppelin/contracts/access/Ownable.sol",
      "solcConfig": {
        "version": "0.8.4",
        "settings": {
          "optimizer": {
            "enabled": false,
            "runs": 200
          },
          "outputSelection": {
            "*": {
              "*": [
                "abi",
                "evm.bytecode",
                "evm.deployedBytecode",
                "evm.methodIdentifiers"
              ],
              "": [
                "ast"
              ]
            }
          }
        }
      },
      "imports": [
        "../utils/Context.sol"
      ],
      "versionPragmas": [
        "^0.8.0"
      ],
      "artifacts": [
        "Ownable"
      ]
    },
    "/home/ubuntu1/web3go/mintynew/node_modules/@openzeppelin/contracts/token/ERC721/IERC721.sol": {
      "lastModificationDate": 1628667868399,
      "contentHash": "93a5aa8a276e028a4f46f22b5d8f7bd3",
      "sourceName": "@openzeppelin/contracts/token/ERC721/IERC721.sol",
      "solcConfig": {
        "version": "0.8.4",
        "settings": {
          "optimizer": {
            "enabled": false,
            "runs": 200
          },
          "outputSelection": {
            "*": {
              "*": [
                "abi",
                "evm.bytecode",
                "evm.deployedBytecode",
                "evm.methodIdentifiers"
              ],
              "": [
                "ast"
              ]
            }
          }
        }
      },
      "imports": [
        "../../utils/introspection/IERC165.sol"
      ],
      "versionPragmas": [
        "^0.8.0"
      ],
      "artifacts": [
        "IERC721"
      ]
    },
    "/home/ubuntu1/web3go/mintynew/node_modules/@openzeppelin/contracts/token/ERC721/IERC721Receiver.sol": {
      "lastModificationDate": 1628667868399,
      "contentHash": "e6d69a0b5b95ac1112eb4746a2d66f3e",
      "sourceName": "@openzeppelin/contracts/token/ERC721/IERC721Receiver.sol",
      "solcConfig": {
        "version": "0.8.4",
        "settings": {
          "optimizer": {
            "enabled": false,
            "runs": 200
          },
          "outputSelection": {
            "*": {
              "*": [
                "abi",
                "evm.bytecode",
                "evm.deployedBytecode",
                "evm.methodIdentifiers"
              ],
              "": [
                "ast"
              ]
            }
          }
        }
      },
      "imports": [],
      "versionPragmas": [
        "^0.8.0"
      ],
      "artifacts": [
        "IERC721Receiver"
      ]
    },
    "/home/ubuntu1/web3go/mintynew/node_modules/@openzeppelin/contracts/token/ERC721/extensions/IERC721Metadata.sol": {
      "lastModificationDate": 1628667868399,
      "contentHash": "75cedcb24edaec014d2071ed59a03ff3",
      "sourceName": "@openzeppelin/contracts/token/ERC721/extensions/IERC721Metadata.sol",
      "solcConfig": {
        "version": "0.8.4",
        "settings": {
          "optimizer": {
            "enabled": false,
            "runs": 200
          },
          "outputSelection": {
            "*": {
              "*": [
                "abi",
                "evm.bytecode",
                "evm.deployedBytecode",
                "evm.methodIdentifiers"
              ],
              "": [
                "ast"
              ]
            }
          }
        }
      },
      "imports": [
        "../IERC721.sol"
      ],
      "versionPragmas": [
        "^0.8.0"
      ],
      "artifacts": [
        "IERC721Metadata"
      ]
    },
    "/home/ubuntu1/web3go/mintynew/node_modules/@openzeppelin/contracts/utils/Address.sol": {
      "lastModificationDate": 1628667868399,
      "contentHash": "37103cdc416efc2601c6f6734044b559",
      "sourceName": "@openzeppelin/contracts/utils/Address.sol",
      "solcConfig": {
        "version": "0.8.4",
        "settings": {
          "optimizer": {
            "enabled": false,
            "runs": 200
          },
          "outputSelection": {
            "*": {
              "*": [
                "abi",
                "evm.bytecode",
                "evm.deployedBytecode",
                "evm.methodIdentifiers"
              ],
              "": [
                "ast"
              ]
            }
          }
        }
      },
      "imports": [],
      "versionPragmas": [
        "^0.8.0"
      ],
      "artifacts": [
        "Address"
      ]
    },
    "/home/ubuntu1/web3go/mintynew/node_modules/@openzeppelin/contracts/utils/Context.sol": {
      "lastModificationDate": 1628667868399,
      "contentHash": "bc047f55d4e6dcc5a9c7ee096f530312",
      "sourceName": "@openzeppelin/contracts/utils/Context.sol",
      "solcConfig": {
        "version": "0.8.4",
        "settings": {
          "optimizer": {
            "enabled": false,
            "runs": 200
          },
          "outputSelection": {
            "*": {
              "*": [
                "abi",
                "evm.bytecode",
                "evm.deployedBytecode",
                "evm.methodIdentifiers"
              ],
              "": [
                "ast"
              ]
            }
          }
        }
      },
      "imports": [],
      "versionPragmas": [
        "^0.8.0"
      ],
      "artifacts": [
        "Context"
      ]
    },
    "/home/ubuntu1/web3go/mintynew/node_modules/@openzeppelin/contracts/utils/Strings.sol": {
      "lastModificationDate": 1628667868399,
      "contentHash": "e575d915a7dbf0decd510699a7fd53dc",
      "sourceName": "@openzeppelin/contracts/utils/Strings.sol",
      "solcConfig": {
        "version": "0.8.4",
        "settings": {
          "optimizer": {
            "enabled": false,
            "runs": 200
          },
          "outputSelection": {
            "*": {
              "*": [
                "abi",
                "evm.bytecode",
                "evm.deployedBytecode",
                "evm.methodIdentifiers"
              ],
              "": [
                "ast"
              ]
            }
          }
        }
      },
      "imports": [],
      "versionPragmas": [
        "^0.8.0"
      ],
      "artifacts": [
        "Strings"
      ]
    },
    "/home/ubuntu1/web3go/mintynew/node_modules/@openzeppelin/contracts/utils/introspection/ERC165.sol": {
      "lastModificationDate": 1628667868399,
      "contentHash": "a9a5319dff9088c6ffe757ea1c2a6729",
      "sourceName": "@openzeppelin/contracts/utils/introspection/ERC165.sol",
      "solcConfig": {
        "version": "0.8.4",
        "settings": {
          "optimizer": {
            "enabled": false,
            "runs": 200
          },
          "outputSelection": {
            "*": {
              "*": [
                "abi",
                "evm.bytecode",
                "evm.deployedBytecode",
                "evm.methodIdentifiers"
              ],
              "": [
                "ast"
              ]
            }
          }
        }
      },
      "imports": [
        "./IERC165.sol"
      ],
      "versionPragmas": [
        "^0.8.0"
      ],
      "artifacts": [
        "ERC165"
      ]
    },
    "/home/ubuntu1/web3go/mintynew/node_modules/@openzeppelin/contracts/utils/introspection/IERC165.sol": {
      "lastModificationDate": 1628667868399,
      "contentHash": "9a04322bb8f6b8f2767d8358d1d2537b",
      "sourceName": "@openzeppelin/contracts/utils/introspection/IERC165.sol",
      "solcConfig": {
        "version": "0.8.4",
        "settings": {
          "optimizer": {
            "enabled": false,
            "runs": 200
          },
          "outputSelection": {
            "*": {
              "*": [
                "abi",
                "evm.bytecode",
                "evm.deployedBytecode",
                "evm.methodIdentifiers"
              ],
              "": [
                "ast"
              ]
            }
          }
        }
      },
      "imports": [],
      "versionPragmas": [
        "^0.8.0"
      ],
      "artifacts": [
        "IERC165"
      ]
    },
    "/home/ubuntu1/web3go/mintynew/contracts/STARNFT11.sol": {
      "lastModificationDate": 1628689769580,
      "contentHash": "2e23df9dad46a3ae5b964091a60e91a3",
      "sourceName": "contracts/STARNFT11.sol",
      "solcConfig": {
        "version": "0.8.4",
        "settings": {
          "optimizer": {
            "enabled": false,
            "runs": 200
          },
          "outputSelection": {
            "*": {
              "*": [
                "abi",
                "evm.bytecode",
                "evm.deployedBytecode",
                "evm.methodIdentifiers"
              ],
              "": [
                "ast"
              ]
            }
          }
        }
      },
      "imports": [
        "@openzeppelin/contracts/token/ERC721/ERC721.sol",
        "@openzeppelin/contracts/utils/Counters.sol",
        "@openzeppelin/contracts/access/Ownable.sol"
      ],
      "versionPragmas": [
        "^0.8.0"
      ],
      "artifacts": [
        "STARNFT11"
      ]
    },
    "/home/ubuntu1/web3go/mintynew/contracts/STARNFT12.sol": {
      "lastModificationDate": 1628689778064,
      "contentHash": "0f6416c10327cc02d614c2b3cc53e9be",
      "sourceName": "contracts/STARNFT12.sol",
      "solcConfig": {
        "version": "0.8.4",
        "settings": {
          "optimizer": {
            "enabled": false,
            "runs": 200
          },
          "outputSelection": {
            "*": {
              "*": [
                "abi",
                "evm.bytecode",
                "evm.deployedBytecode",
                "evm.methodIdentifiers"
              ],
              "": [
                "ast"
              ]
            }
          }
        }
      },
      "imports": [
        "@openzeppelin/contracts/token/ERC721/ERC721.sol",
        "@openzeppelin/contracts/utils/Counters.sol",
        "@openzeppelin/contracts/access/Ownable.sol"
      ],
      "versionPragmas": [
        "^0.8.0"
      ],
      "artifacts": [
        "STARNFT12"
      ]
    },
    "/home/ubuntu1/web3go/mintynew/contracts/STARNFT14.sol": {
      "lastModificationDate": 1628765801772,
      "contentHash": "33d9a840935a4e0d195e5cb52c83faf0",
      "sourceName": "contracts/STARNFT14.sol",
      "solcConfig": {
        "version": "0.8.4",
        "settings": {
          "optimizer": {
            "enabled": false,
            "runs": 200
          },
          "outputSelection": {
            "*": {
              "*": [
                "abi",
                "evm.bytecode",
                "evm.deployedBytecode",
                "evm.methodIdentifiers"
              ],
              "": [
                "ast"
              ]
            }
          }
        }
      },
      "imports": [
        "@openzeppelin/contracts/token/ERC721/ERC721.sol",
        "@openzeppelin/contracts/utils/Counters.sol",
        "@openzeppelin/contracts/access/Ownable.sol"
      ],
      "versionPragmas": [
        "^0.8.0"
      ],
      "artifacts": [
        "STARNFT14"
      ]
    },
    "/home/ubuntu1/web3go/mintynew/contracts/ERC721Pausable.sol": {
      "lastModificationDate": 1628849164063,
      "contentHash": "b60c0e711a637b83e94439868cf24c8c",
      "sourceName": "contracts/ERC721Pausable.sol",
      "solcConfig": {
        "version": "0.8.4",
        "settings": {
          "optimizer": {
            "enabled": false,
            "runs": 200
          },
          "outputSelection": {
            "*": {
              "*": [
                "abi",
                "evm.bytecode",
                "evm.deployedBytecode",
                "evm.methodIdentifiers"
              ],
              "": [
                "ast"
              ]
            }
          }
        }
      },
      "imports": [
        "@openzeppelin/contracts/token/ERC721/ERC721.sol",
        "@openzeppelin/contracts/security/Pausable.sol",
        "@openzeppelin/contracts/access/Ownable.sol"
      ],
      "versionPragmas": [
        "^0.8.0"
      ],
      "artifacts": [
        "ERC721Pausable"
      ]
    },
    "/home/ubuntu1/web3go/mintynew/node_modules/@openzeppelin/contracts/security/Pausable.sol": {
      "lastModificationDate": 1628667868399,
      "contentHash": "835673b68fdeaf41b38c84e966e8630b",
      "sourceName": "@openzeppelin/contracts/security/Pausable.sol",
      "solcConfig": {
        "version": "0.8.4",
        "settings": {
          "optimizer": {
            "enabled": false,
            "runs": 200
          },
          "outputSelection": {
            "*": {
              "*": [
                "abi",
                "evm.bytecode",
                "evm.deployedBytecode",
                "evm.methodIdentifiers"
              ],
              "": [
                "ast"
              ]
            }
          }
        }
      },
      "imports": [
        "../utils/Context.sol"
      ],
      "versionPragmas": [
        "^0.8.0"
      ],
      "artifacts": [
        "Pausable"
      ]
    },
    "/home/ubuntu1/web3go/mintynew/node_modules/@openzeppelin/contracts/token/ERC721/extensions/ERC721Enumerable.sol": {
      "lastModificationDate": 1628667868399,
      "contentHash": "11629722b0e3c53cb55733af5176cd33",
      "sourceName": "@openzeppelin/contracts/token/ERC721/extensions/ERC721Enumerable.sol",
      "solcConfig": {
        "version": "0.8.4",
        "settings": {
          "optimizer": {
            "enabled": false,
            "runs": 200
          },
          "outputSelection": {
            "*": {
              "*": [
                "abi",
                "evm.bytecode",
                "evm.deployedBytecode",
                "evm.methodIdentifiers"
              ],
              "": [
                "ast"
              ]
            }
          }
        }
      },
      "imports": [
        "../ERC721.sol",
        "./IERC721Enumerable.sol"
      ],
      "versionPragmas": [
        "^0.8.0"
      ],
      "artifacts": [
        "ERC721Enumerable"
      ]
    },
    "/home/ubuntu1/web3go/mintynew/node_modules/@openzeppelin/contracts/token/ERC721/extensions/ERC721Burnable.sol": {
      "lastModificationDate": 1628667868399,
      "contentHash": "c451d6197061b5e0d446b7171af0dc01",
      "sourceName": "@openzeppelin/contracts/token/ERC721/extensions/ERC721Burnable.sol",
      "solcConfig": {
        "version": "0.8.4",
        "settings": {
          "optimizer": {
            "enabled": false,
            "runs": 200
          },
          "outputSelection": {
            "*": {
              "*": [
                "abi",
                "evm.bytecode",
                "evm.deployedBytecode",
                "evm.methodIdentifiers"
              ],
              "": [
                "ast"
              ]
            }
          }
        }
      },
      "imports": [
        "../ERC721.sol",
        "../../../utils/Context.sol"
      ],
      "versionPragmas": [
        "^0.8.0"
      ],
      "artifacts": [
        "ERC721Burnable"
      ]
    },
    "/home/ubuntu1/web3go/mintynew/node_modules/@openzeppelin/contracts/utils/math/SafeMath.sol": {
      "lastModificationDate": 1628667868403,
      "contentHash": "9f282272a197e5e800ef035117e86f2f",
      "sourceName": "@openzeppelin/contracts/utils/math/SafeMath.sol",
      "solcConfig": {
        "version": "0.8.4",
        "settings": {
          "optimizer": {
            "enabled": false,
            "runs": 200
          },
          "outputSelection": {
            "*": {
              "*": [
                "abi",
                "evm.bytecode",
                "evm.deployedBytecode",
                "evm.methodIdentifiers"
              ],
              "": [
                "ast"
              ]
            }
          }
        }
      },
      "imports": [],
      "versionPragmas": [
        "^0.8.0"
      ],
      "artifacts": [
        "SafeMath"
      ]
    },
    "/home/ubuntu1/web3go/mintynew/node_modules/@openzeppelin/contracts/token/ERC721/extensions/IERC721Enumerable.sol": {
      "lastModificationDate": 1628667868399,
      "contentHash": "f2ae82a09cc670ca19d644f60990b94d",
      "sourceName": "@openzeppelin/contracts/token/ERC721/extensions/IERC721Enumerable.sol",
      "solcConfig": {
        "version": "0.8.4",
        "settings": {
          "optimizer": {
            "enabled": false,
            "runs": 200
          },
          "outputSelection": {
            "*": {
              "*": [
                "abi",
                "evm.bytecode",
                "evm.deployedBytecode",
                "evm.methodIdentifiers"
              ],
              "": [
                "ast"
              ]
            }
          }
        }
      },
      "imports": [
        "../IERC721.sol"
      ],
      "versionPragmas": [
        "^0.8.0"
      ],
      "artifacts": [
        "IERC721Enumerable"
      ]
    },
    "/home/ubuntu1/web3go/mintynew/contracts/STARIVERPudgyPenguins10.sol": {
      "lastModificationDate": 1628862230023,
      "contentHash": "04d1872a6f9138b34f82180841c6d450",
      "sourceName": "contracts/STARIVERPudgyPenguins10.sol",
      "solcConfig": {
        "version": "0.8.4",
        "settings": {
          "optimizer": {
            "enabled": false,
            "runs": 200
          },
          "outputSelection": {
            "*": {
              "*": [
                "abi",
                "evm.bytecode",
                "evm.deployedBytecode",
                "evm.methodIdentifiers"
              ],
              "": [
                "ast"
              ]
            }
          }
        }
      },
      "imports": [
        "@openzeppelin/contracts/token/ERC721/ERC721.sol",
        "@openzeppelin/contracts/token/ERC721/extensions/ERC721Enumerable.sol",
        "@openzeppelin/contracts/token/ERC721/extensions/ERC721Burnable.sol",
        "@openzeppelin/contracts/access/Ownable.sol",
        "@openzeppelin/contracts/utils/math/SafeMath.sol",
        "@openzeppelin/contracts/utils/Counters.sol",
        "./ERC721Pausable.sol"
      ],
      "versionPragmas": [
        "^0.8.0"
      ],
      "artifacts": [
        "STARIVERPudgyPenguins10"
      ]
    }
  }
}
